setup.cfg
setup.py
datacrypt/__init__.py
datacrypt/cronServer.py
datacrypt/instance.py
datacrypt/paramsHandling.py
datacrypt/server.py
datacrypt/utils.py
datacrypt.egg-info/PKG-INFO
datacrypt.egg-info/SOURCES.txt
datacrypt.egg-info/dependency_links.txt
datacrypt.egg-info/not-zip-safe
datacrypt.egg-info/requires.txt
datacrypt.egg-info/top_level.txt
datacrypt/codeme/__init__.py
datacrypt/codeme/admin.py
datacrypt/codeme/auth2.py
datacrypt/codeme/changed.py
datacrypt/codeme/db.py
datacrypt/codeme/dbAdmin.py
datacrypt/codeme/dbUtils.py
datacrypt/codeme/fileRunner.py
datacrypt/codeme/folderRunner.py
datacrypt/codeme/git.py
datacrypt/codeme/hashing.py
datacrypt/codeme/hide.py
datacrypt/codeme/otp.py
datacrypt/codeme/purge.py
datacrypt/codeme/show.py
datacrypt/codeme/sslKey.py
datacrypt/codeme/status.py
datacrypt/codeme/uattributes.py
datacrypt/codeme/update.py
datacrypt/codeme/utils.py
datacrypt/copier/__init__.py
datacrypt/variant4/__init__.py
datacrypt/variant4/utils.py
datacrypt/web/__init__.py
datacrypt/web/static/css/2.ded2dc51.chunk.css
datacrypt/web/static/css/2.ded2dc51.chunk.css.map
datacrypt/web/static/css/main.208bcb81.chunk.css
datacrypt/web/static/css/main.208bcb81.chunk.css.map
datacrypt/web/static/js/2.2abd8b5e.chunk.js
datacrypt/web/static/js/2.2abd8b5e.chunk.js.LICENSE.txt
datacrypt/web/static/js/2.2abd8b5e.chunk.js.map
datacrypt/web/static/js/3.de68b601.chunk.js
datacrypt/web/static/js/3.de68b601.chunk.js.map
datacrypt/web/static/js/main.fdf9a3b6.chunk.js
datacrypt/web/static/js/main.fdf9a3b6.chunk.js.map
datacrypt/web/static/js/runtime-main.526c8eca.js
datacrypt/web/static/js/runtime-main.526c8eca.js.map
datacrypt/web/templates/index.html